[
  [
    {
      "Integer": {
        "U32OracleValue": {
          "placeholder": "PcInit"
        }
      }
    },
    {
      "Integer": {
        "TruncateFromU32": {
          "U32SubExpression": 0
        }
      }
    },
    {
      "WriteVariable": {
        "into_variable": 0,
        "source_subexpr": {
          "U16": {
            "U16SubExpression": 1
          }
        },
        "condition_subexpr_idx": null
      }
    },
    {
      "Integer": {
        "WrappingShr": {
          "lhs": {
            "U32SubExpression": 0
          },
          "magnitude": 16
        }
      }
    },
    {
      "Integer": {
        "TruncateFromU32": {
          "U32SubExpression": 3
        }
      }
    },
    {
      "WriteVariable": {
        "into_variable": 1,
        "source_subexpr": {
          "U16": {
            "U16SubExpression": 4
          }
        },
        "condition_subexpr_idx": null
      }
    }
  ],
  [
    {
      "Integer": {
        "U32OracleValue": {
          "placeholder": "FirstRegMem"
        }
      }
    },
    {
      "Integer": {
        "TruncateFromU32": {
          "U32SubExpression": 0
        }
      }
    },
    {
      "WriteVariable": {
        "into_variable": 17,
        "source_subexpr": {
          "U16": {
            "U16SubExpression": 1
          }
        },
        "condition_subexpr_idx": null
      }
    },
    {
      "Integer": {
        "WrappingShr": {
          "lhs": {
            "U32SubExpression": 0
          },
          "magnitude": 16
        }
      }
    },
    {
      "Integer": {
        "TruncateFromU32": {
          "U32SubExpression": 3
        }
      }
    },
    {
      "WriteVariable": {
        "into_variable": 18,
        "source_subexpr": {
          "U16": {
            "U16SubExpression": 4
          }
        },
        "condition_subexpr_idx": null
      }
    }
  ],
  [
    {
      "Integer": {
        "U16Place": 9
      }
    },
    {
      "Integer": {
        "U16Place": 10
      }
    },
    {
      "Integer": {
        "U16Place": 17
      }
    },
    {
      "Integer": {
        "U16Place": 18
      }
    },
    {
      "Integer": {
        "WidenFromU16": {
          "U16SubExpression": 3
        }
      }
    },
    {
      "Integer": {
        "WrappingShl": {
          "lhs": {
            "U32SubExpression": 4
          },
          "magnitude": 16
        }
      }
    },
    {
      "Integer": {
        "WidenFromU16": {
          "U16SubExpression": 2
        }
      }
    },
    {
      "Integer": {
        "WrappingAdd": {
          "lhs": {
            "U32SubExpression": 5
          },
          "rhs": {
            "U32SubExpression": 6
          }
        }
      }
    },
    {
      "Integer": {
        "WidenFromU16": {
          "U16SubExpression": 1
        }
      }
    },
    {
      "Integer": {
        "WrappingShl": {
          "lhs": {
            "U32SubExpression": 8
          },
          "magnitude": 16
        }
      }
    },
    {
      "Integer": {
        "WidenFromU16": {
          "U16SubExpression": 0
        }
      }
    },
    {
      "Integer": {
        "WrappingAdd": {
          "lhs": {
            "U32SubExpression": 9
          },
          "rhs": {
            "U32SubExpression": 10
          }
        }
      }
    },
    {
      "Integer": {
        "WrappingAdd": {
          "lhs": {
            "U32SubExpression": 7
          },
          "rhs": {
            "U32SubExpression": 11
          }
        }
      }
    },
    {
      "Integer": {
        "TruncateFromU32": {
          "U32SubExpression": 12
        }
      }
    },
    {
      "WriteVariable": {
        "into_variable": 19,
        "source_subexpr": {
          "U16": {
            "U16SubExpression": 13
          }
        },
        "condition_subexpr_idx": null
      }
    },
    {
      "Integer": {
        "WrappingShr": {
          "lhs": {
            "U32SubExpression": 12
          },
          "magnitude": 16
        }
      }
    },
    {
      "Integer": {
        "TruncateFromU32": {
          "U32SubExpression": 15
        }
      }
    },
    {
      "WriteVariable": {
        "into_variable": 20,
        "source_subexpr": {
          "U16": {
            "U16SubExpression": 16
          }
        },
        "condition_subexpr_idx": null
      }
    },
    {
      "Bool": {
        "FromGenericIntegerCarry": {
          "lhs": {
            "U32SubExpression": 7
          },
          "rhs": {
            "U32SubExpression": 11
          }
        }
      }
    },
    {
      "WriteVariable": {
        "into_variable": 21,
        "source_subexpr": {
          "Bool": {
            "SubExpression": 18
          }
        },
        "condition_subexpr_idx": null
      }
    }
  ],
  [
    {
      "Field": {
        "Place": 8
      }
    },
    {
      "Field": {
        "Place": 11
      }
    },
    {
      "Field": {
        "Place": 12
      }
    },
    {
      "Field": {
        "Place": 19
      }
    },
    {
      "Field": {
        "Constant": 524288
      }
    },
    {
      "Field": {
        "Constant": 1048576
      }
    },
    {
      "Field": {
        "AddProduct": {
          "additive_term": {
            "SubExpression": 4
          },
          "mul_0": {
            "SubExpression": 5
          },
          "mul_1": {
            "SubExpression": 0
          }
        }
      }
    },
    {
      "Field": {
        "Constant": 65536
      }
    },
    {
      "Field": {
        "AddProduct": {
          "additive_term": {
            "SubExpression": 6
          },
          "mul_0": {
            "SubExpression": 7
          },
          "mul_1": {
            "SubExpression": 1
          }
        }
      }
    },
    {
      "Field": {
        "Constant": 2146959359
      }
    },
    {
      "Field": {
        "AddProduct": {
          "additive_term": {
            "SubExpression": 8
          },
          "mul_0": {
            "SubExpression": 9
          },
          "mul_1": {
            "SubExpression": 2
          }
        }
      }
    },
    {
      "Field": {
        "Constant": 1
      }
    },
    {
      "Field": {
        "AddProduct": {
          "additive_term": {
            "SubExpression": 10
          },
          "mul_0": {
            "SubExpression": 11
          },
          "mul_1": {
            "SubExpression": 3
          }
        }
      }
    },
    {
      "Integer": {
        "ConstantU16": 44
      }
    },
    {
      "PerformLookup": {
        "input_subexpr_idxes": [
          12
        ],
        "table_id_subexpr_idx": 13,
        "num_outputs": 2,
        "lookup_mapping_idx": 0
      }
    },
    {
      "AccessLookup": {
        "subindex": 14,
        "output_index": 0
      }
    },
    {
      "WriteVariable": {
        "into_variable": 22,
        "source_subexpr": {
          "Field": {
            "SubExpression": 15
          }
        },
        "condition_subexpr_idx": null
      }
    },
    {
      "AccessLookup": {
        "subindex": 14,
        "output_index": 1
      }
    },
    {
      "WriteVariable": {
        "into_variable": 23,
        "source_subexpr": {
          "Field": {
            "SubExpression": 17
          }
        },
        "condition_subexpr_idx": null
      }
    }
  ],
  [
    {
      "Field": {
        "Place": 23
      }
    },
    {
      "Integer": {
        "U32FromField": {
          "SubExpression": 0
        }
      }
    },
    {
      "Integer": {
        "LowestBits": {
          "value": {
            "U32SubExpression": 1
          },
          "num_bits": 1
        }
      }
    },
    {
      "Bool": {
        "FromGenericInteger": {
          "U32SubExpression": 2
        }
      }
    },
    {
      "WriteVariable": {
        "into_variable": 24,
        "source_subexpr": {
          "Bool": {
            "SubExpression": 3
          }
        },
        "condition_subexpr_idx": null
      }
    },
    {
      "Integer": {
        "WrappingShr": {
          "lhs": {
            "U32SubExpression": 1
          },
          "magnitude": 1
        }
      }
    },
    {
      "Integer": {
        "LowestBits": {
          "value": {
            "U32SubExpression": 5
          },
          "num_bits": 1
        }
      }
    },
    {
      "Bool": {
        "FromGenericInteger": {
          "U32SubExpression": 6
        }
      }
    },
    {
      "WriteVariable": {
        "into_variable": 25,
        "source_subexpr": {
          "Bool": {
            "SubExpression": 7
          }
        },
        "condition_subexpr_idx": null
      }
    }
  ],
  [
    {
      "Field": {
        "Place": 20
      }
    },
    {
      "Field": {
        "Constant": 0
      }
    },
    {
      "Field": {
        "Constant": 1
      }
    },
    {
      "Field": {
        "AddProduct": {
          "additive_term": {
            "SubExpression": 1
          },
          "mul_0": {
            "SubExpression": 2
          },
          "mul_1": {
            "SubExpression": 0
          }
        }
      }
    },
    {
      "Integer": {
        "ConstantU16": 23
      }
    },
    {
      "PerformLookup": {
        "input_subexpr_idxes": [
          3
        ],
        "table_id_subexpr_idx": 4,
        "num_outputs": 2,
        "lookup_mapping_idx": 1
      }
    },
    {
      "AccessLookup": {
        "subindex": 5,
        "output_index": 0
      }
    },
    {
      "WriteVariable": {
        "into_variable": 26,
        "source_subexpr": {
          "Field": {
            "SubExpression": 6
          }
        },
        "condition_subexpr_idx": null
      }
    },
    {
      "AccessLookup": {
        "subindex": 5,
        "output_index": 1
      }
    },
    {
      "WriteVariable": {
        "into_variable": 27,
        "source_subexpr": {
          "Field": {
            "SubExpression": 8
          }
        },
        "condition_subexpr_idx": null
      }
    }
  ],
  [
    {
      "Field": {
        "Place": 12
      }
    },
    {
      "Field": {
        "Place": 26
      }
    },
    {
      "Field": {
        "Constant": 1
      }
    },
    {
      "Field": {
        "AddProduct": {
          "additive_term": {
            "SubExpression": 2
          },
          "mul_0": {
            "SubExpression": 0
          },
          "mul_1": {
            "SubExpression": 1
          }
        }
      }
    },
    {
      "Field": {
        "Sub": {
          "lhs": {
            "SubExpression": 3
          },
          "rhs": {
            "SubExpression": 0
          }
        }
      }
    },
    {
      "Field": {
        "Sub": {
          "lhs": {
            "SubExpression": 4
          },
          "rhs": {
            "SubExpression": 1
          }
        }
      }
    },
    {
      "WriteVariable": {
        "into_variable": 28,
        "source_subexpr": {
          "Field": {
            "SubExpression": 5
          }
        },
        "condition_subexpr_idx": null
      }
    }
  ],
  [
    {
      "Field": {
        "Place": 12
      }
    },
    {
      "Field": {
        "Place": 26
      }
    },
    {
      "Field": {
        "Constant": 0
      }
    },
    {
      "Field": {
        "Mul": {
          "lhs": {
            "SubExpression": 0
          },
          "rhs": {
            "SubExpression": 1
          }
        }
      }
    },
    {
      "Field": {
        "Sub": {
          "lhs": {
            "SubExpression": 2
          },
          "rhs": {
            "SubExpression": 3
          }
        }
      }
    },
    {
      "Field": {
        "Add": {
          "lhs": {
            "SubExpression": 4
          },
          "rhs": {
            "SubExpression": 1
          }
        }
      }
    },
    {
      "WriteVariable": {
        "into_variable": 29,
        "source_subexpr": {
          "Field": {
            "SubExpression": 5
          }
        },
        "condition_subexpr_idx": null
      }
    }
  ],
  [
    {
      "Field": {
        "Place": 6
      }
    },
    {
      "Field": {
        "Place": 12
      }
    },
    {
      "Field": {
        "Place": 19
      }
    },
    {
      "Field": {
        "Place": 22
      }
    },
    {
      "Field": {
        "Constant": 0
      }
    },
    {
      "Field": {
        "AddProduct": {
          "additive_term": {
            "SubExpression": 4
          },
          "mul_0": {
            "SubExpression": 0
          },
          "mul_1": {
            "SubExpression": 1
          }
        }
      }
    },
    {
      "Field": {
        "AddProduct": {
          "additive_term": {
            "SubExpression": 5
          },
          "mul_0": {
            "SubExpression": 1
          },
          "mul_1": {
            "SubExpression": 3
          }
        }
      }
    },
    {
      "Field": {
        "Mul": {
          "lhs": {
            "SubExpression": 1
          },
          "rhs": {
            "SubExpression": 2
          }
        }
      }
    },
    {
      "Field": {
        "Sub": {
          "lhs": {
            "SubExpression": 6
          },
          "rhs": {
            "SubExpression": 7
          }
        }
      }
    },
    {
      "Field": {
        "Add": {
          "lhs": {
            "SubExpression": 8
          },
          "rhs": {
            "SubExpression": 2
          }
        }
      }
    },
    {
      "Field": {
        "Sub": {
          "lhs": {
            "SubExpression": 9
          },
          "rhs": {
            "SubExpression": 3
          }
        }
      }
    },
    {
      "WriteVariable": {
        "into_variable": 30,
        "source_subexpr": {
          "Field": {
            "SubExpression": 10
          }
        },
        "condition_subexpr_idx": null
      }
    }
  ],
  [
    {
      "Field": {
        "Place": 12
      }
    },
    {
      "Field": {
        "Place": 20
      }
    },
    {
      "Field": {
        "Constant": 0
      }
    },
    {
      "Field": {
        "Mul": {
          "lhs": {
            "SubExpression": 0
          },
          "rhs": {
            "SubExpression": 1
          }
        }
      }
    },
    {
      "Field": {
        "Sub": {
          "lhs": {
            "SubExpression": 2
          },
          "rhs": {
            "SubExpression": 3
          }
        }
      }
    },
    {
      "Field": {
        "Add": {
          "lhs": {
            "SubExpression": 4
          },
          "rhs": {
            "SubExpression": 1
          }
        }
      }
    },
    {
      "WriteVariable": {
        "into_variable": 31,
        "source_subexpr": {
          "Field": {
            "SubExpression": 5
          }
        },
        "condition_subexpr_idx": null
      }
    }
  ],
  [
    {
      "Field": {
        "Place": 12
      }
    },
    {
      "Field": {
        "Constant": 1
      }
    },
    {
      "Field": {
        "Sub": {
          "lhs": {
            "SubExpression": 1
          },
          "rhs": {
            "SubExpression": 0
          }
        }
      }
    },
    {
      "WriteVariable": {
        "into_variable": 34,
        "source_subexpr": {
          "Field": {
            "SubExpression": 2
          }
        },
        "condition_subexpr_idx": null
      }
    }
  ],
  [
    {
      "Field": {
        "Place": 7
      }
    },
    {
      "Field": {
        "Place": 12
      }
    },
    {
      "Field": {
        "Place": 19
      }
    },
    {
      "Field": {
        "Place": 22
      }
    },
    {
      "Field": {
        "Constant": 0
      }
    },
    {
      "Field": {
        "AddProduct": {
          "additive_term": {
            "SubExpression": 4
          },
          "mul_0": {
            "SubExpression": 1
          },
          "mul_1": {
            "SubExpression": 2
          }
        }
      }
    },
    {
      "Field": {
        "Mul": {
          "lhs": {
            "SubExpression": 0
          },
          "rhs": {
            "SubExpression": 1
          }
        }
      }
    },
    {
      "Field": {
        "Sub": {
          "lhs": {
            "SubExpression": 5
          },
          "rhs": {
            "SubExpression": 6
          }
        }
      }
    },
    {
      "Field": {
        "Mul": {
          "lhs": {
            "SubExpression": 1
          },
          "rhs": {
            "SubExpression": 3
          }
        }
      }
    },
    {
      "Field": {
        "Sub": {
          "lhs": {
            "SubExpression": 7
          },
          "rhs": {
            "SubExpression": 8
          }
        }
      }
    },
    {
      "Field": {
        "Add": {
          "lhs": {
            "SubExpression": 9
          },
          "rhs": {
            "SubExpression": 0
          }
        }
      }
    },
    {
      "WriteVariable": {
        "into_variable": 35,
        "source_subexpr": {
          "Field": {
            "SubExpression": 10
          }
        },
        "condition_subexpr_idx": null
      }
    }
  ],
  [
    {
      "Field": {
        "Place": 12
      }
    },
    {
      "Field": {
        "Place": 20
      }
    },
    {
      "Field": {
        "Constant": 0
      }
    },
    {
      "Field": {
        "AddProduct": {
          "additive_term": {
            "SubExpression": 2
          },
          "mul_0": {
            "SubExpression": 0
          },
          "mul_1": {
            "SubExpression": 1
          }
        }
      }
    },
    {
      "WriteVariable": {
        "into_variable": 36,
        "source_subexpr": {
          "Field": {
            "SubExpression": 3
          }
        },
        "condition_subexpr_idx": null
      }
    }
  ],
  [
    {
      "Field": {
        "Place": 19
      }
    },
    {
      "Field": {
        "Place": 22
      }
    },
    {
      "Field": {
        "Place": 27
      }
    },
    {
      "Bool": {
        "Place": 28
      }
    },
    {
      "Field": {
        "Constant": 0
      }
    },
    {
      "Field": {
        "Constant": 536870912
      }
    },
    {
      "Field": {
        "AddProduct": {
          "additive_term": {
            "SubExpression": 4
          },
          "mul_0": {
            "SubExpression": 5
          },
          "mul_1": {
            "SubExpression": 0
          }
        }
      }
    },
    {
      "Field": {
        "Constant": 1610612735
      }
    },
    {
      "Field": {
        "AddProduct": {
          "additive_term": {
            "SubExpression": 6
          },
          "mul_0": {
            "SubExpression": 7
          },
          "mul_1": {
            "SubExpression": 1
          }
        }
      }
    },
    {
      "Field": {
        "Constant": 16384
      }
    },
    {
      "Field": {
        "AddProduct": {
          "additive_term": {
            "SubExpression": 8
          },
          "mul_0": {
            "SubExpression": 9
          },
          "mul_1": {
            "SubExpression": 2
          }
        }
      }
    },
    {
      "Integer": {
        "ConstantU16": 46
      }
    },
    {
      "MaybePerformLookup": {
        "input_subexpr_idxes": [
          10
        ],
        "table_id_subexpr_idx": 11,
        "mask_id_subexpr_idx": 3,
        "num_outputs": 2
      }
    },
    {
      "AccessLookup": {
        "subindex": 12,
        "output_index": 0
      }
    },
    {
      "WriteVariable": {
        "into_variable": 41,
        "source_subexpr": {
          "Field": {
            "SubExpression": 13
          }
        },
        "condition_subexpr_idx": 3
      }
    },
    {
      "AccessLookup": {
        "subindex": 12,
        "output_index": 1
      }
    },
    {
      "WriteVariable": {
        "into_variable": 42,
        "source_subexpr": {
          "Field": {
            "SubExpression": 15
          }
        },
        "condition_subexpr_idx": 3
      }
    }
  ],
  [
    {
      "Bool": {
        "Place": 25
      }
    },
    {
      "Field": {
        "Place": 32
      }
    },
    {
      "Field": {
        "Place": 33
      }
    },
    {
      "Field": {
        "Select": {
          "selector": {
            "SubExpression": 0
          },
          "if_true": {
            "SubExpression": 2
          },
          "if_false": {
            "SubExpression": 1
          }
        }
      }
    },
    {
      "WriteVariable": {
        "into_variable": 46,
        "source_subexpr": {
          "Field": {
            "SubExpression": 3
          }
        },
        "condition_subexpr_idx": null
      }
    }
  ],
  [
    {
      "Field": {
        "Place": 11
      }
    },
    {
      "Field": {
        "Place": 22
      }
    },
    {
      "Bool": {
        "Place": 29
      }
    },
    {
      "Field": {
        "Place": 46
      }
    },
    {
      "Field": {
        "Constant": 0
      }
    },
    {
      "Field": {
        "Constant": 262144
      }
    },
    {
      "Field": {
        "AddProduct": {
          "additive_term": {
            "SubExpression": 4
          },
          "mul_0": {
            "SubExpression": 5
          },
          "mul_1": {
            "SubExpression": 0
          }
        }
      }
    },
    {
      "Field": {
        "Constant": 65536
      }
    },
    {
      "Field": {
        "AddProduct": {
          "additive_term": {
            "SubExpression": 6
          },
          "mul_0": {
            "SubExpression": 7
          },
          "mul_1": {
            "SubExpression": 1
          }
        }
      }
    },
    {
      "Field": {
        "Constant": 1
      }
    },
    {
      "Field": {
        "AddProduct": {
          "additive_term": {
            "SubExpression": 8
          },
          "mul_0": {
            "SubExpression": 9
          },
          "mul_1": {
            "SubExpression": 3
          }
        }
      }
    },
    {
      "Integer": {
        "ConstantU16": 45
      }
    },
    {
      "MaybePerformLookup": {
        "input_subexpr_idxes": [
          10
        ],
        "table_id_subexpr_idx": 11,
        "mask_id_subexpr_idx": 2,
        "num_outputs": 2
      }
    },
    {
      "AccessLookup": {
        "subindex": 12,
        "output_index": 0
      }
    },
    {
      "WriteVariable": {
        "into_variable": 41,
        "source_subexpr": {
          "Field": {
            "SubExpression": 13
          }
        },
        "condition_subexpr_idx": 2
      }
    },
    {
      "AccessLookup": {
        "subindex": 12,
        "output_index": 1
      }
    },
    {
      "WriteVariable": {
        "into_variable": 42,
        "source_subexpr": {
          "Field": {
            "SubExpression": 15
          }
        },
        "condition_subexpr_idx": 2
      }
    }
  ],
  [
    {
      "Bool": {
        "Place": 25
      }
    },
    {
      "Field": {
        "Place": 37
      }
    },
    {
      "Field": {
        "Place": 38
      }
    },
    {
      "Field": {
        "Select": {
          "selector": {
            "SubExpression": 0
          },
          "if_true": {
            "SubExpression": 2
          },
          "if_false": {
            "SubExpression": 1
          }
        }
      }
    },
    {
      "WriteVariable": {
        "into_variable": 47,
        "source_subexpr": {
          "Field": {
            "SubExpression": 3
          }
        },
        "condition_subexpr_idx": null
      }
    }
  ],
  [
    {
      "Field": {
        "Place": 11
      }
    },
    {
      "Bool": {
        "Place": 12
      }
    },
    {
      "Field": {
        "Place": 22
      }
    },
    {
      "Field": {
        "Place": 47
      }
    },
    {
      "Field": {
        "Constant": 0
      }
    },
    {
      "Field": {
        "Constant": 262144
      }
    },
    {
      "Field": {
        "AddProduct": {
          "additive_term": {
            "SubExpression": 4
          },
          "mul_0": {
            "SubExpression": 5
          },
          "mul_1": {
            "SubExpression": 0
          }
        }
      }
    },
    {
      "Field": {
        "Constant": 65536
      }
    },
    {
      "Field": {
        "AddProduct": {
          "additive_term": {
            "SubExpression": 6
          },
          "mul_0": {
            "SubExpression": 7
          },
          "mul_1": {
            "SubExpression": 2
          }
        }
      }
    },
    {
      "Field": {
        "Constant": 1
      }
    },
    {
      "Field": {
        "AddProduct": {
          "additive_term": {
            "SubExpression": 8
          },
          "mul_0": {
            "SubExpression": 9
          },
          "mul_1": {
            "SubExpression": 3
          }
        }
      }
    },
    {
      "Integer": {
        "ConstantU16": 54
      }
    },
    {
      "MaybePerformLookup": {
        "input_subexpr_idxes": [
          10
        ],
        "table_id_subexpr_idx": 11,
        "mask_id_subexpr_idx": 1,
        "num_outputs": 2
      }
    },
    {
      "AccessLookup": {
        "subindex": 12,
        "output_index": 0
      }
    },
    {
      "WriteVariable": {
        "into_variable": 41,
        "source_subexpr": {
          "Field": {
            "SubExpression": 13
          }
        },
        "condition_subexpr_idx": 1
      }
    },
    {
      "AccessLookup": {
        "subindex": 12,
        "output_index": 1
      }
    },
    {
      "WriteVariable": {
        "into_variable": 42,
        "source_subexpr": {
          "Field": {
            "SubExpression": 15
          }
        },
        "condition_subexpr_idx": 1
      }
    }
  ],
  [
    {
      "Field": {
        "Place": 11
      }
    },
    {
      "Bool": {
        "Place": 12
      }
    },
    {
      "Field": {
        "Place": 22
      }
    },
    {
      "Field": {
        "Place": 32
      }
    },
    {
      "Field": {
        "Constant": 0
      }
    },
    {
      "Field": {
        "Constant": 262144
      }
    },
    {
      "Field": {
        "AddProduct": {
          "additive_term": {
            "SubExpression": 4
          },
          "mul_0": {
            "SubExpression": 5
          },
          "mul_1": {
            "SubExpression": 0
          }
        }
      }
    },
    {
      "Field": {
        "Constant": 65536
      }
    },
    {
      "Field": {
        "AddProduct": {
          "additive_term": {
            "SubExpression": 6
          },
          "mul_0": {
            "SubExpression": 7
          },
          "mul_1": {
            "SubExpression": 2
          }
        }
      }
    },
    {
      "Field": {
        "Constant": 1
      }
    },
    {
      "Field": {
        "AddProduct": {
          "additive_term": {
            "SubExpression": 8
          },
          "mul_0": {
            "SubExpression": 9
          },
          "mul_1": {
            "SubExpression": 3
          }
        }
      }
    },
    {
      "Integer": {
        "ConstantU16": 55
      }
    },
    {
      "MaybePerformLookup": {
        "input_subexpr_idxes": [
          10
        ],
        "table_id_subexpr_idx": 11,
        "mask_id_subexpr_idx": 1,
        "num_outputs": 2
      }
    },
    {
      "AccessLookup": {
        "subindex": 12,
        "output_index": 0
      }
    },
    {
      "WriteVariable": {
        "into_variable": 44,
        "source_subexpr": {
          "Field": {
            "SubExpression": 13
          }
        },
        "condition_subexpr_idx": 1
      }
    },
    {
      "AccessLookup": {
        "subindex": 12,
        "output_index": 1
      }
    },
    {
      "WriteVariable": {
        "into_variable": 45,
        "source_subexpr": {
          "Field": {
            "SubExpression": 15
          }
        },
        "condition_subexpr_idx": 1
      }
    }
  ],
  [
    {
      "Field": {
        "Place": 11
      }
    },
    {
      "Bool": {
        "Place": 12
      }
    },
    {
      "Field": {
        "Place": 19
      }
    },
    {
      "Field": {
        "Place": 22
      }
    },
    {
      "Field": {
        "Place": 27
      }
    },
    {
      "Bool": {
        "Place": 28
      }
    },
    {
      "Bool": {
        "Place": 29
      }
    },
    {
      "Field": {
        "Place": 46
      }
    },
    {
      "Field": {
        "Place": 47
      }
    },
    {
      "Field": {
        "Constant": 0
      }
    },
    {
      "Field": {
        "Add": {
          "lhs": {
            "SubExpression": 9
          },
          "rhs": {
            "SubExpression": 8
          }
        }
      }
    },
    {
      "Field": {
        "Select": {
          "selector": {
            "SubExpression": 1
          },
          "if_true": {
            "SubExpression": 10
          },
          "if_false": {
            "SubExpression": 9
          }
        }
      }
    },
    {
      "Field": {
        "Add": {
          "lhs": {
            "SubExpression": 11
          },
          "rhs": {
            "SubExpression": 7
          }
        }
      }
    },
    {
      "Field": {
        "Select": {
          "selector": {
            "SubExpression": 6
          },
          "if_true": {
            "SubExpression": 12
          },
          "if_false": {
            "SubExpression": 11
          }
        }
      }
    },
    {
      "Field": {
        "Constant": 262144
      }
    },
    {
      "Field": {
        "AddProduct": {
          "additive_term": {
            "SubExpression": 13
          },
          "mul_0": {
            "SubExpression": 14
          },
          "mul_1": {
            "SubExpression": 0
          }
        }
      }
    },
    {
      "Field": {
        "Select": {
          "selector": {
            "SubExpression": 1
          },
          "if_true": {
            "SubExpression": 15
          },
          "if_false": {
            "SubExpression": 13
          }
        }
      }
    },
    {
      "Field": {
        "AddProduct": {
          "additive_term": {
            "SubExpression": 16
          },
          "mul_0": {
            "SubExpression": 14
          },
          "mul_1": {
            "SubExpression": 0
          }
        }
      }
    },
    {
      "Field": {
        "Select": {
          "selector": {
            "SubExpression": 6
          },
          "if_true": {
            "SubExpression": 17
          },
          "if_false": {
            "SubExpression": 16
          }
        }
      }
    },
    {
      "Field": {
        "Constant": 65536
      }
    },
    {
      "Field": {
        "AddProduct": {
          "additive_term": {
            "SubExpression": 18
          },
          "mul_0": {
            "SubExpression": 19
          },
          "mul_1": {
            "SubExpression": 3
          }
        }
      }
    },
    {
      "Field": {
        "Select": {
          "selector": {
            "SubExpression": 1
          },
          "if_true": {
            "SubExpression": 20
          },
          "if_false": {
            "SubExpression": 18
          }
        }
      }
    },
    {
      "Field": {
        "Constant": 536870912
      }
    },
    {
      "Field": {
        "AddProduct": {
          "additive_term": {
            "SubExpression": 21
          },
          "mul_0": {
            "SubExpression": 22
          },
          "mul_1": {
            "SubExpression": 2
          }
        }
      }
    },
    {
      "Field": {
        "Select": {
          "selector": {
            "SubExpression": 5
          },
          "if_true": {
            "SubExpression": 23
          },
          "if_false": {
            "SubExpression": 21
          }
        }
      }
    },
    {
      "Field": {
        "Constant": 1610612735
      }
    },
    {
      "Field": {
        "AddProduct": {
          "additive_term": {
            "SubExpression": 24
          },
          "mul_0": {
            "SubExpression": 25
          },
          "mul_1": {
            "SubExpression": 3
          }
        }
      }
    },
    {
      "Field": {
        "Select": {
          "selector": {
            "SubExpression": 5
          },
          "if_true": {
            "SubExpression": 26
          },
          "if_false": {
            "SubExpression": 24
          }
        }
      }
    },
    {
      "Field": {
        "AddProduct": {
          "additive_term": {
            "SubExpression": 27
          },
          "mul_0": {
            "SubExpression": 19
          },
          "mul_1": {
            "SubExpression": 3
          }
        }
      }
    },
    {
      "Field": {
        "Select": {
          "selector": {
            "SubExpression": 6
          },
          "if_true": {
            "SubExpression": 28
          },
          "if_false": {
            "SubExpression": 27
          }
        }
      }
    },
    {
      "Field": {
        "Constant": 16384
      }
    },
    {
      "Field": {
        "AddProduct": {
          "additive_term": {
            "SubExpression": 29
          },
          "mul_0": {
            "SubExpression": 30
          },
          "mul_1": {
            "SubExpression": 4
          }
        }
      }
    },
    {
      "Field": {
        "Select": {
          "selector": {
            "SubExpression": 5
          },
          "if_true": {
            "SubExpression": 31
          },
          "if_false": {
            "SubExpression": 29
          }
        }
      }
    },
    {
      "WriteVariable": {
        "into_variable": 52,
        "source_subexpr": {
          "Field": {
            "SubExpression": 32
          }
        },
        "condition_subexpr_idx": null
      }
    }
  ],
  [
    {
      "Bool": {
        "Place": 12
      }
    },
    {
      "Bool": {
        "Place": 28
      }
    },
    {
      "Bool": {
        "Place": 29
      }
    },
    {
      "Field": {
        "Place": 41
      }
    },
    {
      "Field": {
        "Constant": 0
      }
    },
    {
      "Field": {
        "Add": {
          "lhs": {
            "SubExpression": 4
          },
          "rhs": {
            "SubExpression": 3
          }
        }
      }
    },
    {
      "Field": {
        "Select": {
          "selector": {
            "SubExpression": 0
          },
          "if_true": {
            "SubExpression": 5
          },
          "if_false": {
            "SubExpression": 4
          }
        }
      }
    },
    {
      "Field": {
        "Add": {
          "lhs": {
            "SubExpression": 6
          },
          "rhs": {
            "SubExpression": 3
          }
        }
      }
    },
    {
      "Field": {
        "Select": {
          "selector": {
            "SubExpression": 1
          },
          "if_true": {
            "SubExpression": 7
          },
          "if_false": {
            "SubExpression": 6
          }
        }
      }
    },
    {
      "Field": {
        "Add": {
          "lhs": {
            "SubExpression": 8
          },
          "rhs": {
            "SubExpression": 3
          }
        }
      }
    },
    {
      "Field": {
        "Select": {
          "selector": {
            "SubExpression": 2
          },
          "if_true": {
            "SubExpression": 9
          },
          "if_false": {
            "SubExpression": 8
          }
        }
      }
    },
    {
      "WriteVariable": {
        "into_variable": 53,
        "source_subexpr": {
          "Field": {
            "SubExpression": 10
          }
        },
        "condition_subexpr_idx": null
      }
    }
  ],
  [
    {
      "Bool": {
        "Place": 12
      }
    },
    {
      "Bool": {
        "Place": 28
      }
    },
    {
      "Bool": {
        "Place": 29
      }
    },
    {
      "Field": {
        "Place": 42
      }
    },
    {
      "Field": {
        "Constant": 0
      }
    },
    {
      "Field": {
        "Add": {
          "lhs": {
            "SubExpression": 4
          },
          "rhs": {
            "SubExpression": 3
          }
        }
      }
    },
    {
      "Field": {
        "Select": {
          "selector": {
            "SubExpression": 0
          },
          "if_true": {
            "SubExpression": 5
          },
          "if_false": {
            "SubExpression": 4
          }
        }
      }
    },
    {
      "Field": {
        "Add": {
          "lhs": {
            "SubExpression": 6
          },
          "rhs": {
            "SubExpression": 3
          }
        }
      }
    },
    {
      "Field": {
        "Select": {
          "selector": {
            "SubExpression": 1
          },
          "if_true": {
            "SubExpression": 7
          },
          "if_false": {
            "SubExpression": 6
          }
        }
      }
    },
    {
      "Field": {
        "Add": {
          "lhs": {
            "SubExpression": 8
          },
          "rhs": {
            "SubExpression": 3
          }
        }
      }
    },
    {
      "Field": {
        "Select": {
          "selector": {
            "SubExpression": 2
          },
          "if_true": {
            "SubExpression": 9
          },
          "if_false": {
            "SubExpression": 8
          }
        }
      }
    },
    {
      "WriteVariable": {
        "into_variable": 54,
        "source_subexpr": {
          "Field": {
            "SubExpression": 10
          }
        },
        "condition_subexpr_idx": null
      }
    }
  ],
  [
    {
      "Bool": {
        "Place": 12
      }
    },
    {
      "Bool": {
        "Place": 28
      }
    },
    {
      "Bool": {
        "Place": 29
      }
    },
    {
      "Field": {
        "Constant": 0
      }
    },
    {
      "Field": {
        "Constant": 46
      }
    },
    {
      "Field": {
        "Add": {
          "lhs": {
            "SubExpression": 3
          },
          "rhs": {
            "SubExpression": 4
          }
        }
      }
    },
    {
      "Field": {
        "Select": {
          "selector": {
            "SubExpression": 1
          },
          "if_true": {
            "SubExpression": 5
          },
          "if_false": {
            "SubExpression": 3
          }
        }
      }
    },
    {
      "Field": {
        "Constant": 45
      }
    },
    {
      "Field": {
        "Add": {
          "lhs": {
            "SubExpression": 6
          },
          "rhs": {
            "SubExpression": 7
          }
        }
      }
    },
    {
      "Field": {
        "Select": {
          "selector": {
            "SubExpression": 2
          },
          "if_true": {
            "SubExpression": 8
          },
          "if_false": {
            "SubExpression": 6
          }
        }
      }
    },
    {
      "Field": {
        "Constant": 54
      }
    },
    {
      "Field": {
        "Add": {
          "lhs": {
            "SubExpression": 9
          },
          "rhs": {
            "SubExpression": 10
          }
        }
      }
    },
    {
      "Field": {
        "Select": {
          "selector": {
            "SubExpression": 0
          },
          "if_true": {
            "SubExpression": 11
          },
          "if_false": {
            "SubExpression": 9
          }
        }
      }
    },
    {
      "WriteVariable": {
        "into_variable": 55,
        "source_subexpr": {
          "Field": {
            "SubExpression": 12
          }
        },
        "condition_subexpr_idx": null
      }
    }
  ],
  [
    {
      "Field": {
        "Place": 52
      }
    },
    {
      "Field": {
        "Place": 53
      }
    },
    {
      "Field": {
        "Place": 54
      }
    },
    {
      "Integer": {
        "U16Place": 55
      }
    },
    {
      "PerformLookup": {
        "input_subexpr_idxes": [
          0,
          1,
          2
        ],
        "table_id_subexpr_idx": 3,
        "num_outputs": 0,
        "lookup_mapping_idx": 2
      }
    }
  ],
  [
    {
      "Bool": {
        "Place": 12
      }
    },
    {
      "Bool": {
        "Place": 28
      }
    },
    {
      "Field": {
        "Constant": 0
      }
    },
    {
      "Field": {
        "Constant": 45
      }
    },
    {
      "Field": {
        "Add": {
          "lhs": {
            "SubExpression": 2
          },
          "rhs": {
            "SubExpression": 3
          }
        }
      }
    },
    {
      "Field": {
        "Select": {
          "selector": {
            "SubExpression": 1
          },
          "if_true": {
            "SubExpression": 4
          },
          "if_false": {
            "SubExpression": 2
          }
        }
      }
    },
    {
      "Field": {
        "Constant": 55
      }
    },
    {
      "Field": {
        "Add": {
          "lhs": {
            "SubExpression": 5
          },
          "rhs": {
            "SubExpression": 6
          }
        }
      }
    },
    {
      "Field": {
        "Select": {
          "selector": {
            "SubExpression": 0
          },
          "if_true": {
            "SubExpression": 7
          },
          "if_false": {
            "SubExpression": 5
          }
        }
      }
    },
    {
      "WriteVariable": {
        "into_variable": 59,
        "source_subexpr": {
          "Field": {
            "SubExpression": 8
          }
        },
        "condition_subexpr_idx": null
      }
    }
  ],
  [
    {
      "Integer": {
        "U16Place": 0
      }
    },
    {
      "Integer": {
        "ConstantU16": 4
      }
    },
    {
      "Bool": {
        "FromGenericIntegerCarry": {
          "lhs": {
            "U16SubExpression": 0
          },
          "rhs": {
            "U16SubExpression": 1
          }
        }
      }
    },
    {
      "Integer": {
        "ConstantU16": 0
      }
    },
    {
      "Integer": {
        "WrappingAdd": {
          "lhs": {
            "U16SubExpression": 0
          },
          "rhs": {
            "U16SubExpression": 1
          }
        }
      }
    },
    {
      "Integer": {
        "Select": {
          "selector": {
            "SubExpression": 2
          },
          "if_true": {
            "U16SubExpression": 3
          },
          "if_false": {
            "U16SubExpression": 4
          }
        }
      }
    },
    {
      "WriteVariable": {
        "into_variable": 13,
        "source_subexpr": {
          "U16": {
            "U16SubExpression": 5
          }
        },
        "condition_subexpr_idx": null
      }
    },
    {
      "Integer": {
        "WidenFromU16": {
          "U16SubExpression": 0
        }
      }
    },
    {
      "Field": {
        "FromInteger": {
          "U32SubExpression": 7
        }
      }
    },
    {
      "Field": {
        "Constant": 4
      }
    },
    {
      "Field": {
        "Add": {
          "lhs": {
            "SubExpression": 8
          },
          "rhs": {
            "SubExpression": 9
          }
        }
      }
    },
    {
      "Field": {
        "Constant": 65536
      }
    },
    {
      "Field": {
        "Sub": {
          "lhs": {
            "SubExpression": 10
          },
          "rhs": {
            "SubExpression": 11
          }
        }
      }
    },
    {
      "Field": {
        "InverseOrZero": {
          "SubExpression": 12
        }
      }
    },
    {
      "WriteVariable": {
        "into_variable": 64,
        "source_subexpr": {
          "Field": {
            "SubExpression": 13
          }
        },
        "condition_subexpr_idx": null
      }
    },
    {
      "WriteVariable": {
        "into_variable": 65,
        "source_subexpr": {
          "Bool": {
            "SubExpression": 2
          }
        },
        "condition_subexpr_idx": null
      }
    }
  ],
  [
    {
      "Integer": {
        "U16Place": 1
      }
    },
    {
      "Integer": {
        "U16Place": 65
      }
    },
    {
      "Bool": {
        "FromGenericIntegerCarry": {
          "lhs": {
            "U16SubExpression": 0
          },
          "rhs": {
            "U16SubExpression": 1
          }
        }
      }
    },
    {
      "Integer": {
        "ConstantU16": 0
      }
    },
    {
      "Integer": {
        "WrappingAdd": {
          "lhs": {
            "U16SubExpression": 0
          },
          "rhs": {
            "U16SubExpression": 1
          }
        }
      }
    },
    {
      "Integer": {
        "Select": {
          "selector": {
            "SubExpression": 2
          },
          "if_true": {
            "U16SubExpression": 3
          },
          "if_false": {
            "U16SubExpression": 4
          }
        }
      }
    },
    {
      "WriteVariable": {
        "into_variable": 14,
        "source_subexpr": {
          "U16": {
            "U16SubExpression": 5
          }
        },
        "condition_subexpr_idx": null
      }
    },
    {
      "Integer": {
        "WidenFromU16": {
          "U16SubExpression": 0
        }
      }
    },
    {
      "Field": {
        "FromInteger": {
          "U32SubExpression": 7
        }
      }
    },
    {
      "Integer": {
        "WidenFromU16": {
          "U16SubExpression": 1
        }
      }
    },
    {
      "Field": {
        "FromInteger": {
          "U32SubExpression": 9
        }
      }
    },
    {
      "Field": {
        "Add": {
          "lhs": {
            "SubExpression": 8
          },
          "rhs": {
            "SubExpression": 10
          }
        }
      }
    },
    {
      "Field": {
        "Constant": 65536
      }
    },
    {
      "Field": {
        "Sub": {
          "lhs": {
            "SubExpression": 11
          },
          "rhs": {
            "SubExpression": 12
          }
        }
      }
    },
    {
      "Field": {
        "InverseOrZero": {
          "SubExpression": 13
        }
      }
    },
    {
      "WriteVariable": {
        "into_variable": 66,
        "source_subexpr": {
          "Field": {
            "SubExpression": 14
          }
        },
        "condition_subexpr_idx": null
      }
    },
    {
      "WriteVariable": {
        "into_variable": 67,
        "source_subexpr": {
          "Bool": {
            "SubExpression": 2
          }
        },
        "condition_subexpr_idx": null
      }
    }
  ],
  [
    {
      "Bool": {
        "Place": 25
      }
    },
    {
      "Field": {
        "Place": 41
      }
    },
    {
      "Field": {
        "Place": 42
      }
    },
    {
      "Field": {
        "Select": {
          "selector": {
            "SubExpression": 0
          },
          "if_true": {
            "SubExpression": 2
          },
          "if_false": {
            "SubExpression": 1
          }
        }
      }
    },
    {
      "WriteVariable": {
        "into_variable": 43,
        "source_subexpr": {
          "Field": {
            "SubExpression": 3
          }
        },
        "condition_subexpr_idx": null
      }
    }
  ],
  [
    {
      "Field": {
        "Place": 11
      }
    },
    {
      "Field": {
        "Place": 22
      }
    },
    {
      "Bool": {
        "Place": 28
      }
    },
    {
      "Field": {
        "Place": 43
      }
    },
    {
      "Field": {
        "Constant": 0
      }
    },
    {
      "Field": {
        "Constant": 262144
      }
    },
    {
      "Field": {
        "AddProduct": {
          "additive_term": {
            "SubExpression": 4
          },
          "mul_0": {
            "SubExpression": 5
          },
          "mul_1": {
            "SubExpression": 0
          }
        }
      }
    },
    {
      "Field": {
        "Constant": 65536
      }
    },
    {
      "Field": {
        "AddProduct": {
          "additive_term": {
            "SubExpression": 6
          },
          "mul_0": {
            "SubExpression": 7
          },
          "mul_1": {
            "SubExpression": 1
          }
        }
      }
    },
    {
      "Field": {
        "Constant": 1
      }
    },
    {
      "Field": {
        "AddProduct": {
          "additive_term": {
            "SubExpression": 8
          },
          "mul_0": {
            "SubExpression": 9
          },
          "mul_1": {
            "SubExpression": 3
          }
        }
      }
    },
    {
      "Integer": {
        "ConstantU16": 45
      }
    },
    {
      "MaybePerformLookup": {
        "input_subexpr_idxes": [
          10
        ],
        "table_id_subexpr_idx": 11,
        "mask_id_subexpr_idx": 2,
        "num_outputs": 2
      }
    },
    {
      "AccessLookup": {
        "subindex": 12,
        "output_index": 0
      }
    },
    {
      "WriteVariable": {
        "into_variable": 44,
        "source_subexpr": {
          "Field": {
            "SubExpression": 13
          }
        },
        "condition_subexpr_idx": 2
      }
    },
    {
      "AccessLookup": {
        "subindex": 12,
        "output_index": 1
      }
    },
    {
      "WriteVariable": {
        "into_variable": 45,
        "source_subexpr": {
          "Field": {
            "SubExpression": 15
          }
        },
        "condition_subexpr_idx": 2
      }
    }
  ],
  [
    {
      "Field": {
        "Place": 25
      }
    },
    {
      "Field": {
        "Place": 37
      }
    },
    {
      "Field": {
        "Place": 41
      }
    },
    {
      "Field": {
        "Place": 44
      }
    },
    {
      "Field": {
        "Constant": 0
      }
    },
    {
      "Field": {
        "AddProduct": {
          "additive_term": {
            "SubExpression": 4
          },
          "mul_0": {
            "SubExpression": 0
          },
          "mul_1": {
            "SubExpression": 1
          }
        }
      }
    },
    {
      "Field": {
        "Mul": {
          "lhs": {
            "SubExpression": 0
          },
          "rhs": {
            "SubExpression": 2
          }
        }
      }
    },
    {
      "Field": {
        "Sub": {
          "lhs": {
            "SubExpression": 5
          },
          "rhs": {
            "SubExpression": 6
          }
        }
      }
    },
    {
      "Field": {
        "Mul": {
          "lhs": {
            "SubExpression": 0
          },
          "rhs": {
            "SubExpression": 3
          }
        }
      }
    },
    {
      "Field": {
        "Sub": {
          "lhs": {
            "SubExpression": 7
          },
          "rhs": {
            "SubExpression": 8
          }
        }
      }
    },
    {
      "Field": {
        "Add": {
          "lhs": {
            "SubExpression": 9
          },
          "rhs": {
            "SubExpression": 2
          }
        }
      }
    },
    {
      "Field": {
        "Add": {
          "lhs": {
            "SubExpression": 10
          },
          "rhs": {
            "SubExpression": 3
          }
        }
      }
    },
    {
      "WriteVariable": {
        "into_variable": 48,
        "source_subexpr": {
          "Field": {
            "SubExpression": 11
          }
        },
        "condition_subexpr_idx": null
      }
    }
  ],
  [
    {
      "Field": {
        "Place": 25
      }
    },
    {
      "Field": {
        "Place": 38
      }
    },
    {
      "Field": {
        "Place": 41
      }
    },
    {
      "Field": {
        "Place": 44
      }
    },
    {
      "Field": {
        "Constant": 0
      }
    },
    {
      "Field": {
        "AddProduct": {
          "additive_term": {
            "SubExpression": 4
          },
          "mul_0": {
            "SubExpression": 0
          },
          "mul_1": {
            "SubExpression": 2
          }
        }
      }
    },
    {
      "Field": {
        "AddProduct": {
          "additive_term": {
            "SubExpression": 5
          },
          "mul_0": {
            "SubExpression": 0
          },
          "mul_1": {
            "SubExpression": 3
          }
        }
      }
    },
    {
      "Field": {
        "Mul": {
          "lhs": {
            "SubExpression": 0
          },
          "rhs": {
            "SubExpression": 1
          }
        }
      }
    },
    {
      "Field": {
        "Sub": {
          "lhs": {
            "SubExpression": 6
          },
          "rhs": {
            "SubExpression": 7
          }
        }
      }
    },
    {
      "Field": {
        "Add": {
          "lhs": {
            "SubExpression": 8
          },
          "rhs": {
            "SubExpression": 1
          }
        }
      }
    },
    {
      "WriteVariable": {
        "into_variable": 49,
        "source_subexpr": {
          "Field": {
            "SubExpression": 9
          }
        },
        "condition_subexpr_idx": null
      }
    }
  ],
  [
    {
      "Field": {
        "Place": 24
      }
    },
    {
      "Field": {
        "Place": 32
      }
    },
    {
      "Field": {
        "Place": 48
      }
    },
    {
      "Field": {
        "Constant": 0
      }
    },
    {
      "Field": {
        "AddProduct": {
          "additive_term": {
            "SubExpression": 3
          },
          "mul_0": {
            "SubExpression": 0
          },
          "mul_1": {
            "SubExpression": 2
          }
        }
      }
    },
    {
      "Field": {
        "Mul": {
          "lhs": {
            "SubExpression": 0
          },
          "rhs": {
            "SubExpression": 1
          }
        }
      }
    },
    {
      "Field": {
        "Sub": {
          "lhs": {
            "SubExpression": 4
          },
          "rhs": {
            "SubExpression": 5
          }
        }
      }
    },
    {
      "Field": {
        "Add": {
          "lhs": {
            "SubExpression": 6
          },
          "rhs": {
            "SubExpression": 1
          }
        }
      }
    },
    {
      "WriteVariable": {
        "into_variable": 50,
        "source_subexpr": {
          "Field": {
            "SubExpression": 7
          }
        },
        "condition_subexpr_idx": null
      }
    }
  ],
  [
    {
      "Field": {
        "Place": 24
      }
    },
    {
      "Field": {
        "Place": 33
      }
    },
    {
      "Field": {
        "Place": 49
      }
    },
    {
      "Field": {
        "Constant": 0
      }
    },
    {
      "Field": {
        "AddProduct": {
          "additive_term": {
            "SubExpression": 3
          },
          "mul_0": {
            "SubExpression": 0
          },
          "mul_1": {
            "SubExpression": 2
          }
        }
      }
    },
    {
      "Field": {
        "Mul": {
          "lhs": {
            "SubExpression": 0
          },
          "rhs": {
            "SubExpression": 1
          }
        }
      }
    },
    {
      "Field": {
        "Sub": {
          "lhs": {
            "SubExpression": 4
          },
          "rhs": {
            "SubExpression": 5
          }
        }
      }
    },
    {
      "Field": {
        "Add": {
          "lhs": {
            "SubExpression": 6
          },
          "rhs": {
            "SubExpression": 1
          }
        }
      }
    },
    {
      "WriteVariable": {
        "into_variable": 51,
        "source_subexpr": {
          "Field": {
            "SubExpression": 7
          }
        },
        "condition_subexpr_idx": null
      }
    }
  ],
  [
    {
      "Field": {
        "Place": 11
      }
    },
    {
      "Bool": {
        "Place": 12
      }
    },
    {
      "Field": {
        "Place": 22
      }
    },
    {
      "Bool": {
        "Place": 28
      }
    },
    {
      "Field": {
        "Place": 32
      }
    },
    {
      "Field": {
        "Place": 43
      }
    },
    {
      "Field": {
        "Constant": 0
      }
    },
    {
      "Field": {
        "Add": {
          "lhs": {
            "SubExpression": 6
          },
          "rhs": {
            "SubExpression": 4
          }
        }
      }
    },
    {
      "Field": {
        "Select": {
          "selector": {
            "SubExpression": 1
          },
          "if_true": {
            "SubExpression": 7
          },
          "if_false": {
            "SubExpression": 6
          }
        }
      }
    },
    {
      "Field": {
        "Add": {
          "lhs": {
            "SubExpression": 8
          },
          "rhs": {
            "SubExpression": 5
          }
        }
      }
    },
    {
      "Field": {
        "Select": {
          "selector": {
            "SubExpression": 3
          },
          "if_true": {
            "SubExpression": 9
          },
          "if_false": {
            "SubExpression": 8
          }
        }
      }
    },
    {
      "Field": {
        "Constant": 262144
      }
    },
    {
      "Field": {
        "AddProduct": {
          "additive_term": {
            "SubExpression": 10
          },
          "mul_0": {
            "SubExpression": 11
          },
          "mul_1": {
            "SubExpression": 0
          }
        }
      }
    },
    {
      "Field": {
        "Select": {
          "selector": {
            "SubExpression": 1
          },
          "if_true": {
            "SubExpression": 12
          },
          "if_false": {
            "SubExpression": 10
          }
        }
      }
    },
    {
      "Field": {
        "AddProduct": {
          "additive_term": {
            "SubExpression": 13
          },
          "mul_0": {
            "SubExpression": 11
          },
          "mul_1": {
            "SubExpression": 0
          }
        }
      }
    },
    {
      "Field": {
        "Select": {
          "selector": {
            "SubExpression": 3
          },
          "if_true": {
            "SubExpression": 14
          },
          "if_false": {
            "SubExpression": 13
          }
        }
      }
    },
    {
      "Field": {
        "Constant": 65536
      }
    },
    {
      "Field": {
        "AddProduct": {
          "additive_term": {
            "SubExpression": 15
          },
          "mul_0": {
            "SubExpression": 16
          },
          "mul_1": {
            "SubExpression": 2
          }
        }
      }
    },
    {
      "Field": {
        "Select": {
          "selector": {
            "SubExpression": 1
          },
          "if_true": {
            "SubExpression": 17
          },
          "if_false": {
            "SubExpression": 15
          }
        }
      }
    },
    {
      "Field": {
        "AddProduct": {
          "additive_term": {
            "SubExpression": 18
          },
          "mul_0": {
            "SubExpression": 16
          },
          "mul_1": {
            "SubExpression": 2
          }
        }
      }
    },
    {
      "Field": {
        "Select": {
          "selector": {
            "SubExpression": 3
          },
          "if_true": {
            "SubExpression": 19
          },
          "if_false": {
            "SubExpression": 18
          }
        }
      }
    },
    {
      "WriteVariable": {
        "into_variable": 56,
        "source_subexpr": {
          "Field": {
            "SubExpression": 20
          }
        },
        "condition_subexpr_idx": null
      }
    }
  ],
  [
    {
      "Bool": {
        "Place": 12
      }
    },
    {
      "Bool": {
        "Place": 28
      }
    },
    {
      "Field": {
        "Place": 44
      }
    },
    {
      "Field": {
        "Constant": 0
      }
    },
    {
      "Field": {
        "Add": {
          "lhs": {
            "SubExpression": 3
          },
          "rhs": {
            "SubExpression": 2
          }
        }
      }
    },
    {
      "Field": {
        "Select": {
          "selector": {
            "SubExpression": 0
          },
          "if_true": {
            "SubExpression": 4
          },
          "if_false": {
            "SubExpression": 3
          }
        }
      }
    },
    {
      "Field": {
        "Add": {
          "lhs": {
            "SubExpression": 5
          },
          "rhs": {
            "SubExpression": 2
          }
        }
      }
    },
    {
      "Field": {
        "Select": {
          "selector": {
            "SubExpression": 1
          },
          "if_true": {
            "SubExpression": 6
          },
          "if_false": {
            "SubExpression": 5
          }
        }
      }
    },
    {
      "WriteVariable": {
        "into_variable": 57,
        "source_subexpr": {
          "Field": {
            "SubExpression": 7
          }
        },
        "condition_subexpr_idx": null
      }
    }
  ],
  [
    {
      "Bool": {
        "Place": 12
      }
    },
    {
      "Bool": {
        "Place": 28
      }
    },
    {
      "Field": {
        "Place": 45
      }
    },
    {
      "Field": {
        "Constant": 0
      }
    },
    {
      "Field": {
        "Add": {
          "lhs": {
            "SubExpression": 3
          },
          "rhs": {
            "SubExpression": 2
          }
        }
      }
    },
    {
      "Field": {
        "Select": {
          "selector": {
            "SubExpression": 0
          },
          "if_true": {
            "SubExpression": 4
          },
          "if_false": {
            "SubExpression": 3
          }
        }
      }
    },
    {
      "Field": {
        "Add": {
          "lhs": {
            "SubExpression": 5
          },
          "rhs": {
            "SubExpression": 2
          }
        }
      }
    },
    {
      "Field": {
        "Select": {
          "selector": {
            "SubExpression": 1
          },
          "if_true": {
            "SubExpression": 6
          },
          "if_false": {
            "SubExpression": 5
          }
        }
      }
    },
    {
      "WriteVariable": {
        "into_variable": 58,
        "source_subexpr": {
          "Field": {
            "SubExpression": 7
          }
        },
        "condition_subexpr_idx": null
      }
    }
  ],
  [
    {
      "Field": {
        "Place": 56
      }
    },
    {
      "Field": {
        "Place": 57
      }
    },
    {
      "Field": {
        "Place": 58
      }
    },
    {
      "Integer": {
        "U16Place": 59
      }
    },
    {
      "PerformLookup": {
        "input_subexpr_idxes": [
          0,
          1,
          2
        ],
        "table_id_subexpr_idx": 3,
        "num_outputs": 0,
        "lookup_mapping_idx": 3
      }
    }
  ],
  [
    {
      "Field": {
        "Place": 28
      }
    },
    {
      "Field": {
        "Place": 29
      }
    },
    {
      "Field": {
        "Place": 41
      }
    },
    {
      "Field": {
        "Place": 44
      }
    },
    {
      "Field": {
        "Constant": 0
      }
    },
    {
      "Field": {
        "AddProduct": {
          "additive_term": {
            "SubExpression": 4
          },
          "mul_0": {
            "SubExpression": 0
          },
          "mul_1": {
            "SubExpression": 3
          }
        }
      }
    },
    {
      "Field": {
        "AddProduct": {
          "additive_term": {
            "SubExpression": 5
          },
          "mul_0": {
            "SubExpression": 1
          },
          "mul_1": {
            "SubExpression": 2
          }
        }
      }
    },
    {
      "WriteVariable": {
        "into_variable": 60,
        "source_subexpr": {
          "Field": {
            "SubExpression": 6
          }
        },
        "condition_subexpr_idx": null
      }
    }
  ],
  [
    {
      "Field": {
        "Place": 28
      }
    },
    {
      "Field": {
        "Place": 29
      }
    },
    {
      "Field": {
        "Place": 42
      }
    },
    {
      "Field": {
        "Place": 45
      }
    },
    {
      "Field": {
        "Constant": 0
      }
    },
    {
      "Field": {
        "AddProduct": {
          "additive_term": {
            "SubExpression": 4
          },
          "mul_0": {
            "SubExpression": 0
          },
          "mul_1": {
            "SubExpression": 3
          }
        }
      }
    },
    {
      "Field": {
        "AddProduct": {
          "additive_term": {
            "SubExpression": 5
          },
          "mul_0": {
            "SubExpression": 1
          },
          "mul_1": {
            "SubExpression": 2
          }
        }
      }
    },
    {
      "WriteVariable": {
        "into_variable": 61,
        "source_subexpr": {
          "Field": {
            "SubExpression": 6
          }
        },
        "condition_subexpr_idx": null
      }
    }
  ],
  [
    {
      "Field": {
        "Place": 8
      }
    },
    {
      "Field": {
        "Place": 60
      }
    },
    {
      "Field": {
        "Constant": 0
      }
    },
    {
      "Field": {
        "Mul": {
          "lhs": {
            "SubExpression": 0
          },
          "rhs": {
            "SubExpression": 1
          }
        }
      }
    },
    {
      "Field": {
        "Sub": {
          "lhs": {
            "SubExpression": 2
          },
          "rhs": {
            "SubExpression": 3
          }
        }
      }
    },
    {
      "Field": {
        "Add": {
          "lhs": {
            "SubExpression": 4
          },
          "rhs": {
            "SubExpression": 1
          }
        }
      }
    },
    {
      "WriteVariable": {
        "into_variable": 62,
        "source_subexpr": {
          "Field": {
            "SubExpression": 5
          }
        },
        "condition_subexpr_idx": null
      }
    }
  ],
  [
    {
      "Field": {
        "Place": 8
      }
    },
    {
      "Field": {
        "Place": 61
      }
    },
    {
      "Field": {
        "Constant": 0
      }
    },
    {
      "Field": {
        "Mul": {
          "lhs": {
            "SubExpression": 0
          },
          "rhs": {
            "SubExpression": 1
          }
        }
      }
    },
    {
      "Field": {
        "Sub": {
          "lhs": {
            "SubExpression": 2
          },
          "rhs": {
            "SubExpression": 3
          }
        }
      }
    },
    {
      "Field": {
        "Add": {
          "lhs": {
            "SubExpression": 4
          },
          "rhs": {
            "SubExpression": 1
          }
        }
      }
    },
    {
      "WriteVariable": {
        "into_variable": 63,
        "source_subexpr": {
          "Field": {
            "SubExpression": 5
          }
        },
        "condition_subexpr_idx": null
      }
    }
  ]
]